setup.cfg
setup.py
similarweb/__init__.py
similarweb/helpers.py
similarweb/similarweb.py
similarweb/version.py
similarweb.egg-info/PKG-INFO
similarweb.egg-info/SOURCES.txt
similarweb.egg-info/dependency_links.txt
similarweb.egg-info/requires.txt
similarweb.egg-info/top_level.txt