Metadata-Version: 1.1
Name: similarweb
Version: 1.0.0
Summary: Python client for the SimilarWeb API
Home-page: https://github.com/danwagnerco/similarweb
Author: Dan Wagner
Author-email: danwagnerco@gmail.com
License: UNKNOWN
Keywords: similarweb
Platform: UNKNOWN
Classifier: Development Status :: 3 - Alpha
Classifier: Environment :: Console
Classifier: Intended Audience :: Developers
Classifier: Operating System :: OS Independent
Classifier: Programming Language :: Python
